alibabacloud_lmztest20210529_225743357/__init__.py
alibabacloud_lmztest20210529_225743357/client.py
alibabacloud_lmztest20210529_225743357/models.py
alibabacloud_lmztest20210529_225743357_py2-1.0.4.dist-info/LICENSE
alibabacloud_lmztest20210529_225743357_py2-1.0.4.dist-info/METADATA
alibabacloud_lmztest20210529_225743357_py2-1.0.4.dist-info/WHEEL
alibabacloud_lmztest20210529_225743357_py2-1.0.4.dist-info/top_level.txt
alibabacloud_lmztest20210529_225743357_py2-1.0.4.dist-info/RECORD
