Metadata-Version: 2.1
Name: alibabacloud-lmztest20210529-225743357-py2
Version: 1.0.4
Summary: Alibaba Cloud LmzTest (20210529_225743357) SDK Library for Python2
Home-page: https://github.com/aliyun/alibabacloud-python2-sdk
Author: Alibaba Cloud SDK
Author-email: sdk-team@alibabacloud.com
License: Apache License 2.0
Keywords: alibabacloud,lmztest20210529,225743357,py2
Platform: any
Classifier: Development Status :: 4 - Beta
Classifier: Intended Audience :: Developers
Classifier: License :: OSI Approved :: Apache Software License
Classifier: Programming Language :: Python
Classifier: Programming Language :: Python :: 2
Classifier: Programming Language :: Python :: 2.7
Classifier: Programming Language :: Python :: 3
Classifier: Programming Language :: Python :: 3.4
Classifier: Programming Language :: Python :: 3.5
Classifier: Programming Language :: Python :: 3.6
Classifier: Programming Language :: Python :: 3.7
Classifier: Programming Language :: Python :: 3.8
Classifier: Topic :: Software Development
Requires-Dist: alibabacloud-tea-util-py2 (<1.0.0,>=0.0.2)
Requires-Dist: alibabacloud-tea-openapi-py2 (<1.0.0,>=0.0.2)
Requires-Dist: alibabacloud-endpoint-util-py2 (<1.0.0,>=0.0.1)
